{"Year":[2014,2016,2014,2016,2014,2014,2014,2014,2014,2014,2016],"OBS_STATUS":["A","A","A","A","A","A","A","A","A","A","A"],"UNIT_MULT":["0","0","0","0","0","0","0","0","0","0","0"],"NATURE":["C","C","C","C","C","C","C","C","C","C","C"],"SOURCE_DETAIL":["National_SDG_Report","National_SDG_Report","National_SDG_Report","National_SDG_Report","National_SDG_Report","National_SDG_Report","National_SDG_Report","National_SDG_Report","National_SDG_Report","National_SDG_Report","National_SDG_Report"],"SERIES":["_L_CM_080301_1","_L_CM_080301_1","_L_CM_080301_1","_L_CM_080301_1","_L_CM_080301_1","_L_CM_080301_1","_L_CM_080301_1","_L_CM_080301_1","_L_CM_080301_1","_L_CM_080301_1","_L_CM_080301_1"],"REF_AREA":[null,null,null,null,null,null,null,null,null,null,null],"SEX":["F","F","M","M",null,null,null,null,null,null,null],"EDUCATION_LEV":[null,null,null,null,"ISCED11A_01","ISCED11_1","ISCED11_2","ISCED11_3","AGG_5T8",null,null],"UNIT_MEASURE":["PT","PT","PT","PT","PT","PT","PT","PT","PT","PT","PT"],"GeoCode":[null,null,null,null,null,null,null,null,null,null,null],"Value":[85.3,76.1,75.8,69.1,95.5,92.9,86.4,67.1,42.6,79.9,72.2]}