{"data":{"Year":[2015,2016,2015,2016,2015,2016,2017,2015,2015,2015,2015,2015,2015],"SDG Series":["Primary completion rate (%)","Primary completion rate (%)","Primary completion rate (%)","Primary completion rate (%)","Primary completion rate (%)","Primary completion rate (%)","Primary completion rate (%)","Completion rate at lower secondary level General Education (%)","Completion rate at lower secondary level General Education (%)","Completion rate at lower secondary level General Education (%)","Completion rate at the lower secondary level Technical Education (%)","Completion rate at the lower secondary level Technical Education (%)","Completion rate at the lower secondary level Technical Education (%)"],"Sex":["Female","Female","Male","Male",null,null,null,"Female","Male",null,"Female","Male",null],"Value":[72.8,72.6,79.7,79.4,76.3,76.7,72.5,48.9,57.4,53.2,55.9,62.6,59.3]},"edges":{"From":["SDG Series"],"To":["Sex"]}}