{"data":{"Year":[2016],"Observation status":["Normal value"],"Unit multiplier":["Billions"],"Nature of data points":["Country Data"],"Source details":["National_SDG_Report"],"SERIES":["Public expenditure and Official development aid devoted to the preservation and sustainable exploitation of biodiversity and ecosystems (billion CFA Francs)"],"Reference area":[null],"UNIT_MEASURE":["Local currency"],"GeoCode":[null],"Value":[49.35]},"edges":{"From":["Nature of data points"],"To":["Source details"]}}