{"data":{"Year":[2015,2016,2015,2016,2015,2016,2015,2016,2015,2016,2015,2016],"SERIES":["Proportion of primary schools with access to sanitation facilities (%)","Proportion of primary schools with access to sanitation facilities (%)","Proportion of primary schools with access to water (%)","Proportion of primary schools with access to water (%)","Proportion of primary schools with access to electricity (%)","Proportion of primary schools with access to electricity (%)","Proportion of pre-schools with access to water (%)","Proportion of pre-schools with access to water (%)","Proportion of preschools with access to electricity (%)","Proportion of preschools with access to electricity (%)","Proportion of preschools with access to sanitation facilities (%)","Proportion of preschools with access to sanitation facilities (%)"],"Value":[57,59,42,48,23,28,60,60,46,45,73,70]},"edges":[]}